LICENSE
MANIFEST.in
README.rst
setup.py
watchlion.py
watchlion.egg-info/PKG-INFO
watchlion.egg-info/SOURCES.txt
watchlion.egg-info/dependency_links.txt
watchlion.egg-info/entry_points.txt
watchlion.egg-info/not-zip-safe
watchlion.egg-info/requires.txt
watchlion.egg-info/top_level.txt