Metadata-Version: 1.1
Name: watchlion
Version: 0.3
Summary: Filesystem events monitoring
Home-page: http://github.com/MiCHiLU/watchlion
Author: ENDOH takanao
Author-email: UNKNOWN
License: MIT
Keywords: python filesystem monitoring monitor FSEvents
Platform: UNKNOWN
Classifier: Environment :: Console
Classifier: Intended Audience :: Developers
Classifier: Intended Audience :: System Administrators
Classifier: License :: OSI Approved :: MIT License
Classifier: Natural Language :: English
Classifier: Operating System :: MacOS :: MacOS X
Classifier: Programming Language :: Python
Classifier: Topic :: Software Development :: Libraries
Classifier: Topic :: System :: Monitoring
Classifier: Topic :: System :: Filesystems
Classifier: Topic :: Utilities
Classifier: Programming Language :: Python :: 2.6
Classifier: Programming Language :: Python :: 2.7
Classifier: Programming Language :: Python :: 3
